mcpo/__init__.py
mcpo/main.py
mcpo/tests/__init__.py
mcpo/tests/test_hot_reload.py
mcpo/tests/test_main.py
mcpo/utils/auth.py
mcpo/utils/config_watcher.py
mcpo/utils/headers.py
mcpo/utils/main.py
mcpo/utils/oauth.py
mcpo/utils/oauth_callback.html
mcpo-0.0.18.dist-info/METADATA
mcpo-0.0.18.dist-info/WHEEL
mcpo-0.0.18.dist-info/entry_points.txt
mcpo-0.0.18.dist-info/licenses/LICENSE
mcpo-0.0.18.dist-info/RECORD
