Metadata-Version: 2.4
Name: mcpo
Version: 0.0.18
Summary: A simple, secure MCP-to-OpenAPI proxy server
Author-email: Timothy Jaeryang Baek <tim@openwebui.com>
License-File: LICENSE
Requires-Python: >=3.11
Requires-Dist: click>=8.1.8
Requires-Dist: fastapi>=0.115.12
Requires-Dist: mcp>=1.12.4
Requires-Dist: mcp[cli]>=1.12.4
Requires-Dist: passlib[bcrypt]>=1.7.4
Requires-Dist: pydantic>=2.11.1
Requires-Dist: pyjwt[crypto]>=2.10.1
Requires-Dist: python-dotenv>=1.1.0
Requires-Dist: typer>=0.15.2
Requires-Dist: uvicorn>=0.34.0
Requires-Dist: watchdog>=4.0.0
